{
 "slug": "spa", "round": 12, "gp": "Belgian GP", "flag": "🇧🇪", "date": "19 Jul", "status": "active", "report": true,
 "title": "Circuit de Spa-Francorchamps", "loc": "Stavelot", "cc": "BE", "length": "7.004", "turns": 19, "laps": 44, "drsZones": 2, "elev": "102 m", "topSpeed": "~355", "record": "1:46.286 · BOT ’18",
 "sub": "The longest, fastest test on the calendar. Every corner, the sector splits, DRS zones and the Ardennes geography that makes Spa a drivers’ favourite.",
 "mapFile": "Spa-Francorchamps_of_Belgium.svg", "mapTag": "Official layout · 2022 revision", "mapCredit": "Will Pittenger / Wikimedia Commons · CC BY-SA 3.0", "poleRef": "1:53.159 (Verstappen ’24)", "lat": 50.4437, "lng": 5.9686, "tz": "Europe/Brussels",
 "sessions": [{"date":"2026-07-17","sess":"Fri · Practice + Quali"},{"date":"2026-07-18","sess":"Sat · Practice + Quali"},{"date":"2026-07-19","sess":"Sun · Grand Prix"}], "elevLabel": "102 m swing", "elevMax": 108, "asl0": 399,
 "profile": [[0,35],[0.02,18],[0.05,4],[0.065,2],[0.08,30],[0.11,58],[0.15,85],[0.20,100],[0.24,96],[0.30,80],[0.38,62],[0.45,48],[0.52,33],[0.58,24],[0.62,20],[0.70,30],[0.78,55],[0.86,72],[0.92,55],[0.97,40],[1,35]],
 "sectorsBar": [{"k":"s1","from":0,"to":0.27},{"k":"s2","from":0.27,"to":0.75},{"k":"s3","from":0.75,"to":1}],
 "drs": [{"from":0.08,"to":0.19,"det":0.015,"label":"DRS 1"},{"from":0.965,"to":1,"det":0.87,"label":"DRS 2"}],
 "marks": [[0.02,"La Source"],[0.065,"Eau Rouge"],[0.20,"Les Combes"],[0.45,"Pouhon"],[0.62,"Stavelot"],[0.86,"Blanchimont"]],
 "sectors": [{"k":"s1","name":"Sector 1","corners":"T1–4 · La Source → Kemmel","time":"30.5","char":"La Source hairpin, the flat-out Eau Rouge/Raidillon launch and the long Kemmel Straight to Les Combes."},{"k":"s2","name":"Sector 2","corners":"T5–14 · Les Combes → Campus","time":"54.5","char":"The long, twisting middle: Rivage, the mighty Pouhon, Fagnes and Campus. Downforce-limited and where laps swing."},{"k":"s3","name":"Sector 3","corners":"T15–19 · Stavelot → Bus Stop","time":"28.2","char":"Stavelot and Paul Frère feed the near-flat Blanchimont before the tight Bus Stop chicane onto the line."}],
 "pit": [["Pit location","S/F straight","between Bus Stop (T19) & La Source (T1)"],["Pit-lane loss","~18 s","low for the lap length"],["Speed limit","60 km/h",""],["Typical stops","2 (since 2024 resurface)",""]],
 "tyres": [["C2","Hard"],["C3","Medium"],["C4","Soft"]], "tyreAlloc": "One step softer · C2 / C3 / C4",
 "strat": [["fav","Favoured","2-stop · Medium → Hard → Hard"],["","Alternate","2-stop · Soft → Medium → Hard"],["","Wet risk","Inters/wets always in play (Ardennes)"]],
 "stratNote": "The 2024 resurface raised grip and degradation, tipping Spa firmly toward two stops. The long lap burns a lot of rubber, so the hard (C2) does heavy lifting.",
 "otScore": 4.5, "otWord": "High", "otPct": 90,
 "spots": [["Les Combes (T5)","End of the Kemmel Straight after Eau Rouge + DRS 1. One of F1’s best passing spots."],["Bus Stop (T19)","Heavy braking off the main straight + DRS 2. Late-lunge territory."],["La Source (T1)","Tight hairpin right after the line; switchbacks and opening-lap moves."]],
 "otNote": "One of the easiest tracks to pass on. The FIA even shortened the Kemmel DRS zone in 2024 to stop overtakes being too easy. Slipstream effects are enormous.",
 "corners": [["1","La Source","s1","Slow hairpin","The slowest corner on the lap, a tight 2nd-gear right off the start straight."],["2–4","Eau Rouge / Raidillon","s1","Flat-out esses","Left-right-left compression, flat at 300+ km/h. The most famous sequence in motorsport."],["5","Les Combes","s2","Right (braking)","Top of the Kemmel Straight. Heavy braking and the prime overtaking spot."],["6","Malmedy","s2","Quick left","Fast left that flows out of Les Combes toward Bruxelles."],["7","Bruxelles","s2","Long right hairpin","A tightening downhill right; the exit sets up the long run that follows."],["8–9","Rivage","s2","Downhill right","Double right plunging downhill, hard on the front end."],["10–11","Pouhon","s2","Fast double-left","A long, downhill double-apex left at ~290 km/h. One of F1’s great corners."],["12–13","Fagnes","s2","Quick chicane","Right-left flick that breaks up the middle sector."],["14","Campus","s2","Right","Slow right (a.k.a. Stavelot 1) leading toward the final sector."],["15","Stavelot","s3","Fast right","Quick right at the far point, launching the long run up the hill."],["16","Paul Frère","s3","Fast right","Sweeping uphill right feeding the flat-out approach to Blanchimont."],["17–18","Blanchimont","s3","Very fast left","Near-flat left at ~310 km/h. A real test of nerve."],["19","Bus Stop","s3","Chicane","Tight right-left chicane, the final braking zone and a late-lunge chance."]],
 "geo": [["trees","Heart of the Ardennes","Spa threads through the forested hills of Wallonia, with over 100m of elevation change. A rollercoaster as much as a racetrack."],["trending-up","Eau Rouge / Raidillon","The most famous sequence in motorsport: a compression that rockets uphill, taken flat at 300+ km/h."],["cloud-rain","The weather lottery","At 7km, one sector can be soaked while another stays dry. Many great races (1998, 2008, 2021) were decided by rain."],["gauge","Setup tightrope","Sectors 1 and 3 want low drag; the sector 2 sweeps want downforce. Teams pick a compromise wing level."]]
}
